{
  "$schema": "https://developer.microsoft.com/json-schemas/fabric/item/report/definition/visualContainer/1.1.0/schema.json",
  "name": "e950a78466a9857d9c33",
  "position": {
    "x": 949.53846153846155,
    "y": 19.076923076923077,
    "z": 16000,
    "height": 32,
    "width": 111.38461538461539,
    "tabOrder": 17000
  },
  "visual": {
    "visualType": "actionButton",
    "objects": {
      "icon": [
        {
          "properties": {
            "shapeType": {
              "expr": {
                "Literal": {
                  "Value": "'clearAllSlicers'"
                }
              }
            },
            "lineColor": {
              "solid": {
                "color": {
                  "expr": {
                    "ThemeDataColor": {
                      "ColorId": 1,
                      "Percent": 0
                    }
                  }
                }
              }
            },
            "lineWeight": {
              "expr": {
                "Literal": {
                  "Value": "1L"
                }
              }
            },
            "lineTransparency": {
              "expr": {
                "Literal": {
                  "Value": "0D"
                }
              }
            }
          },
          "selector": {
            "id": "default"
          }
        },
        {
          "properties": {
            "shapeType": {
              "expr": {
                "Literal": {
                  "Value": "'clearAllSlicers'"
                }
              }
            },
            "lineColor": {
              "solid": {
                "color": {
                  "expr": {
                    "ThemeDataColor": {
                      "ColorId": 1,
                      "Percent": 0.2
                    }
                  }
                }
              }
            }
          },
          "selector": {
            "id": "hover"
          }
        }
      ],
      "text": [
        {
          "properties": {
            "show": {
              "expr": {
                "Literal": {
                  "Value": "true"
                }
              }
            }
          }
        },
        {
          "properties": {
            "text": {
              "expr": {
                "Literal": {
                  "Value": "'Reset Page'"
                }
              }
            }
          },
          "selector": {
            "id": "hover"
          }
        },
        {
          "properties": {
            "text": {
              "expr": {
                "Literal": {
                  "Value": "'Reset Page'"
                }
              }
            },
            "fontColor": {
              "solid": {
                "color": {
                  "expr": {
                    "ThemeDataColor": {
                      "ColorId": 1,
                      "Percent": 0
                    }
                  }
                }
              }
            }
          },
          "selector": {
            "id": "default"
          }
        }
      ]
    },
    "visualContainerObjects": {
      "visualLink": [
        {
          "properties": {
            "show": {
              "expr": {
                "Literal": {
                  "Value": "true"
                }
              }
            },
            "type": {
              "expr": {
                "Literal": {
                  "Value": "'Bookmark'"
                }
              }
            },
            "navigationSection": {
              "expr": {
                "Literal": {
                  "Value": "'8dab264cb29fb8bcea78'"
                }
              }
            },
            "bookmark": {
              "expr": {
                "Literal": {
                  "Value": "'240f80372a7083b6c8ec'"
                }
              }
            },
            "showDefaultTooltip": {
              "expr": {
                "Literal": {
                  "Value": "true"
                }
              }
            },
            "tooltip": {
              "expr": {
                "Literal": {
                  "Value": "'Revert the page to its initial state'"
                }
              }
            }
          }
        }
      ]
    },
    "drillFilterOtherVisuals": true
  },
  "howCreated": "InsertVisualButton"
}