{
  "$schema": "https://developer.microsoft.com/json-schemas/fabric/item/report/definition/visualContainer/1.1.0/schema.json",
  "name": "bc63df37a6cc17a3164c",
  "position": {
    "x": 84.92307692307692,
    "y": 560,
    "z": 1000,
    "height": 40.615384615384613,
    "width": 464.61538461538464,
    "tabOrder": 19000
  },
  "visual": {
    "visualType": "textbox",
    "objects": {
      "general": [
        {
          "properties": {
            "paragraphs": [
              {
                "textRuns": [
                  {
                    "value": "Cost & Margin Pressure ",
                    "textStyle": {
                      "fontStyle": "italic",
                      "fontSize": "18pt",
                      "color": "#744ec2"
                    }
                  },
                  {
                    "value": "(Financial Stress) ",
                    "textStyle": {
                      "fontStyle": "italic",
                      "fontSize": "14pt",
                      "color": "#744ec2"
                    }
                  },
                  {
                    "value": "🔒",
                    "textStyle": {
                      "fontSize": "14pt",
                      "color": "#744ec2"
                    }
                  }
                ]
              }
            ]
          }
        }
      ]
    },
    "visualContainerObjects": {
      "background": [
        {
          "properties": {
            "show": {
              "expr": {
                "Literal": {
                  "Value": "false"
                }
              }
            }
          }
        }
      ],
      "title": [
        {
          "properties": {
            "text": {
              "expr": {
                "Literal": {
                  "Value": "'Cost & Margin Pressure (Financial Stress)'"
                }
              }
            }
          }
        }
      ]
    },
    "drillFilterOtherVisuals": true
  }
}